dbt_mcp/__init__.py
dbt_mcp/__main__.py
dbt_mcp/main.py
dbt_mcp/py.typed
dbt_mcp/config/config.py
dbt_mcp/dbt_cli/tools.py
dbt_mcp/discovery/client.py
dbt_mcp/discovery/tools.py
dbt_mcp/gql/errors.py
dbt_mcp/lightdash/__init__.py
dbt_mcp/lightdash/client.py
dbt_mcp/lightdash/explore_selector.py
dbt_mcp/lightdash/mapping.py
dbt_mcp/lightdash/prompts.py
dbt_mcp/lightdash/query_builder.py
dbt_mcp/lightdash/resources.py
dbt_mcp/lightdash/semantic_catalog.py
dbt_mcp/lightdash/tools.py
dbt_mcp/lightdash/transformer.py
dbt_mcp/lightdash/types.py
dbt_mcp/lightdash/validation.py
dbt_mcp/mcp/create.py
dbt_mcp/mcp/server.py
dbt_mcp/prompts/__init__.py
dbt_mcp/prompts/prompts.py
dbt_mcp/prompts/dbt_cli/build.md
dbt_mcp/prompts/dbt_cli/compile.md
dbt_mcp/prompts/dbt_cli/docs.md
dbt_mcp/prompts/dbt_cli/list.md
dbt_mcp/prompts/dbt_cli/parse.md
dbt_mcp/prompts/dbt_cli/run.md
dbt_mcp/prompts/dbt_cli/show.md
dbt_mcp/prompts/dbt_cli/test.md
dbt_mcp/prompts/dbt_cli/args/limit.md
dbt_mcp/prompts/dbt_cli/args/resource_type.md
dbt_mcp/prompts/dbt_cli/args/selectors.md
dbt_mcp/prompts/dbt_cli/args/sql_query.md
dbt_mcp/prompts/discovery/get_all_models.md
dbt_mcp/prompts/discovery/get_mart_models.md
dbt_mcp/prompts/discovery/get_model_children.md
dbt_mcp/prompts/discovery/get_model_details.md
dbt_mcp/prompts/discovery/get_model_parents.md
dbt_mcp/prompts/lightdash/TEMPLATE.md
dbt_mcp/prompts/lightdash/create_chart.md
dbt_mcp/prompts/lightdash/create_dashboard.md
dbt_mcp/prompts/lightdash/delete_chart.md
dbt_mcp/prompts/lightdash/delete_dashboard.md
dbt_mcp/prompts/lightdash/edit_chart.md
dbt_mcp/prompts/lightdash/edit_dashboard.md
dbt_mcp/prompts/lightdash/get_chart.md
dbt_mcp/prompts/lightdash/get_dashboard.md
dbt_mcp/prompts/lightdash/get_embed_url.md
dbt_mcp/prompts/lightdash/get_explore.md
dbt_mcp/prompts/lightdash/get_user.md
dbt_mcp/prompts/lightdash/list_charts.md
dbt_mcp/prompts/lightdash/list_dashboards.md
dbt_mcp/prompts/lightdash/list_explores.md
dbt_mcp_lightdash-0.15.0.dist-info/METADATA
dbt_mcp_lightdash-0.15.0.dist-info/WHEEL
dbt_mcp_lightdash-0.15.0.dist-info/entry_points.txt
dbt_mcp_lightdash-0.15.0.dist-info/licenses/LICENSE
dbt_mcp_lightdash-0.15.0.dist-info/RECORD
