Metadata-Version: 2.4
Name: dbt-mcp-lightdash
Version: 0.15.0
Summary: Enhanced MCP server for dbt with Lightdash integration for visualization and chart management.
Project-URL: Documentation, https://github.com/bratko1234/dbt-mcp#readme
Project-URL: Issues, https://github.com/bratko1234/dbt-mcp/issues
Project-URL: Source, https://github.com/bratko1234/dbt-mcp
Project-URL: Original, https://github.com/dbt-labs/dbt-mcp
Author-email: Brat <brat@inceptly.com>
License:                                  Apache License
License-File: LICENSE
Classifier: Development Status :: 4 - Beta
Classifier: Intended Audience :: Developers
Classifier: License :: OSI Approved :: Apache Software License
Classifier: Operating System :: OS Independent
Classifier: Programming Language :: Python :: 3
Requires-Python: >=3.10
Requires-Dist: httpx
Requires-Dist: mcp[cli]==1.10.1
Requires-Dist: pandas==2.2.3
Requires-Dist: pydantic-settings==2.10.1
Requires-Dist: pyyaml==6.0.2
Requires-Dist: requests==2.32.4
Provides-Extra: dbt
Requires-Dist: dbt-protos==1.0.317; extra == 'dbt'
Requires-Dist: dbt-sl-sdk[sync]==0.11.0; extra == 'dbt'
Requires-Dist: dbtlabs-vortex==0.2.0; extra == 'dbt'
Provides-Extra: dspy
Requires-Dist: dspy-ai>=2.4.0; extra == 'dspy'
Requires-Dist: openai>=1.0.0; extra == 'dspy'
